audbcards/__init__.py
audbcards/core/__init__.py
audbcards/core/config.py
audbcards/core/datacard.py
audbcards/core/dataset.py
audbcards/core/utils.py
audbcards/core/templates/datacard.j2
audbcards/core/templates/datacard_description.j2
audbcards/core/templates/datacard_example.j2
audbcards/core/templates/datacard_header.j2
audbcards/core/templates/datacard_schemes.j2
audbcards/core/templates/datacard_tables.j2
audbcards/core/templates/datasets.j2
audbcards/sphinx/__init__.py
audbcards/sphinx/table-preview.css
audbcards/sphinx/table-preview.js
audbcards-0.4.1.dist-info/licenses/LICENSE
docs/changelog.rst
docs/conf.py
docs/contributing.rst
docs/index.rst
docs/install.rst
docs/sphinx-extension.rst
docs/_templates/datacard_header.j2
docs/api-src/audbcards.rst
docs/images/file-duration-distribution.png
tests/conftest.py
tests/test_datacard.py
tests/test_dataset.py
tests/test_fixtures.py
tests/test_utils.py
tests/test_data/rendered_templates/bare_db.rst
tests/test_data/rendered_templates/json_db.rst
tests/test_data/rendered_templates/medium_db.rst
tests/test_data/rendered_templates/minimal_db.rst
tests/test_data/rendered_templates/mixed_db.rst
audbcards-0.4.1.dist-info/METADATA
audbcards-0.4.1.dist-info/WHEEL
audbcards-0.4.1.dist-info/top_level.txt
audbcards-0.4.1.dist-info/RECORD
