Metadata-Version: 2.4
Name: audbcards
Version: 0.4.1
Summary: Create data cards for audb databases
Author: BahaEddine Abrougui
Author-email: Hagen Wierstorf <hwierstorf@audeering.com>, Christian Geng <cgeng@audeering.com>
License: MIT License
Project-URL: repository, https://github.com/audeering/audbcards/
Project-URL: documentation, https://audeering.github.io/audbcards/
Keywords: audio,data,annotation,mlops,machine learning,documentation
Classifier: Development Status :: 4 - Beta
Classifier: Intended Audience :: Science/Research
Classifier: Intended Audience :: Developers
Classifier: License :: OSI Approved :: MIT License
Classifier: Operating System :: OS Independent
Classifier: Programming Language :: Python
Classifier: Programming Language :: Python :: 3
Classifier: Programming Language :: Python :: 3.10
Classifier: Programming Language :: Python :: 3.11
Classifier: Programming Language :: Python :: 3.12
Classifier: Programming Language :: Python :: 3.13
Classifier: Topic :: Scientific/Engineering
Requires-Python: >=3.10
License-File: LICENSE
Requires-Dist: audb>=1.7.0
Requires-Dist: audeer>=2.2.0
Requires-Dist: audiofile>=1.5.0
Requires-Dist: audplot>=1.4.6
Requires-Dist: jinja2
Requires-Dist: pandas>=2.1.0
Requires-Dist: toml
Dynamic: license-file
